[
  {
    "id": 1,
    "productCode": 1,
    "productName": "시그니처 퍼퓸 코튼 썩세스",
    "productSelect": "코튼 썩쎄스 단품",
    "price": 49000,
    "productOption": "코튼 썩쎄스"
  },
  {
    "id": 2,
    "productCode": 1,
    "productName": "시그니처 퍼퓸 코튼 썩세스",
    "productSelect": "코튼 썩쎄스 세트",
    "price": 69000,
    "productOption": "(30%) 퍼퓸+퍼퓸로션(+20,000원)"
  },
  {
    "id": 3,
    "productCode": 1,
    "productName": "시그니처 퍼퓸 코튼 썩세스",
    "productSelect": "[레이어링추천] 향수 세트",
    "price": 85900,
    "productOption": "(26%) 코튼썩세스+코튼허그(+36,900원)"
  },
  {
    "id": 4,
    "productCode": 1,
    "productName": "시그니처 퍼퓸 코튼 썩세스",
    "productSelect": "[레이어링추천] 향수 세트",
    "price": 85900,
    "productOption": "코튼썩세스+코튼키스(+36,900원)"
  },
  {
    "id": 5,
    "productCode": 2,
    "productName": "시그니처 퍼퓸 피그 누아",
    "productSelect": "시그니처 퍼퓸 피그누아",
    "price": 49000,
    "productOption": "퍼퓸 1개 (+코튼메모리 미니어처 증정)"
  },
  {
    "id": 6,
    "productCode": 3,
    "productName": "시그니처 퍼퓸 상탈 레인",
    "productSelect": "향수 단품",
    "price": 49000,
    "productOption": "상탈레인 1개"
  },
  {
    "id": 7,
    "productCode": 3,
    "productName": "시그니처 퍼퓸 상탈 레인",
    "productSelect": "[EVENT] 레이어링 세트",
    "price": 98000,
    "productOption": "상탈레인+피그누아 (+상탈레인 9ml/스톤디퓨저 증정)(+49,000원"
  },
  {
    "id": 8,
    "productCode": 3,
    "productName": "시그니처 퍼퓸 상탈 레인",
    "productSelect": "[EVENT] 레이어링 세트",
    "price": 98000,
    "productOption": "상탈레인+바질테라스 (+상탈레인 9ml/스톤디퓨저 증정)"
  },
  {
    "id": 9,
    "productCode": 3,
    "productName": "시그니처 퍼퓸 상탈 레인",
    "productSelect": "[EVENT] 퍼퓸샤워 세트",
    "price": 68000,
    "productOption": "상탈레인+바질테라스 퍼퓸샤워 (+스톤디퓨저 증정)"
  },
  {
    "id": 10,
    "productCode": 4,
    "productName": "시그니처 퍼퓸 바질 테라스",
    "productSelect": "향수 단품",
    "price": 49000,
    "productOption": "바질테라스 1개"
  },
  {
    "id": 11,
    "productCode": 4,
    "productName": "시그니처 퍼퓸 바질 테라스",
    "productSelect": "[EVENT] 레이어링 세트",
    "price": 98000,
    "productOption": "바질테라스+피그누아 (+상탈레인 9ml/스톤디퓨저 증정)(+49,000원)"
  },
  {
    "id": 12,
    "productCode": 4,
    "productName": "시그니처 퍼퓸 바질 테라스",
    "productSelect": "[EVENT] 레이어링 세트",
    "price": 98000,
    "productOption": "바질테라스+상탈레인(+상탈레인 9ml/스톤디퓨저 증정)(+49,000원)"
  },
  {
    "id": 13,
    "productCode": 4,
    "productName": "시그니처 퍼퓸 바질 테라스",
    "productSelect": "[EVENT] 퍼퓸샤워 세트",
    "price": 68000,
    "productOption": "바질테라스 퍼퓸+퍼퓸샤워 (+스톤디퓨저 증정)(+19,000원)"
  },
  {
    "id": 14,
    "productCode": 5,
    "productName": "퍼퓸 샤워 바질 테라스",
    "productSelect": "퍼퓸샤워 바질테라스",
    "price": 24000,
    "productOption": "퍼퓸샤워 1개"
  },
  {
    "id": 15,
    "productCode": 5,
    "productName": "퍼퓸 샤워 바질 테라스",
    "productSelect": "퍼퓸샤워 바질테라스",
    "price": 45000,
    "productOption": "퍼퓸샤워 바질테라스/퍼퓸샤워 2개(+21,000원)"
  },
  {
    "id": 16,
    "productCode": 5,
    "productName": "퍼퓸 샤워 바질 테라스",
    "productSelect": "퍼퓸샤워 바질테라스",
    "price": 68000,
    "productOption": "퍼퓸 샤워 + 퍼퓸_바질테라스(+스톤디퓨저 증정)(+44,000원)"
  },
  {
    "id": 17,
    "productCode": 6,
    "productName": "시그니처 퍼퓸 코튼허그",
    "productSelect": "향수 단품",
    "price": 49000,
    "productOption": "코튼허그 1개"
  },
  {
    "id": 18,
    "productCode": 6,
    "productName": "시그니처 퍼퓸 코튼허그",
    "productSelect": "코튼허그 세트",
    "price": 65000,
    "productOption": "(25%) 퍼퓸+핸드크림(+16,000원)"
  },
  {
    "id": 19,
    "productCode": 6,
    "productName": "시그니처 퍼퓸 코튼허그",
    "productSelect": "코튼허그 세트",
    "price": 69000,
    "productOption": "(30%) 퍼퓸+퍼퓸샤워(+20,000원)"
  },
  {
    "id": 20,
    "productCode": 6,
    "productName": "시그니처 퍼퓸 코튼허그",
    "productSelect": "코튼허그 세트",
    "price": 69000,
    "productOption": "(30%) 퍼퓸+퍼퓸로션(+20,000원)"
  },
  {
    "id": 21,
    "productCode": 6,
    "productName": "시그니처 퍼퓸 코튼허그",
    "productSelect": "[레이어링추천] 향수 세트",
    "price": 86000,
    "productOption": "(23%) 코튼허그+코튼키스(+37,000원)"
  },
  {
    "id": 22,
    "productCode": 6,
    "productName": "시그니처 퍼퓸 코튼허그",
    "productSelect": "[레이어링추천] 향수 세트",
    "price": 95500,
    "productOption": "(23%) 코튼허그+코튼메모리(+46,500원)"
  },
  {
    "id": 23,
    "productCode": 6,
    "productName": "시그니처 퍼퓸 코튼허그",
    "productSelect": "[레이어링추천] 향수 세트",
    "price": 95500,
    "productOption": "(23%) 코튼허그+코튼디어나잇(+46,500원)"
  },
  {
    "id": 24,
    "productCode": 6,
    "productName": "시그니처 퍼퓸 코튼허그",
    "productSelect": "[레이어링추천] 향수 세트",
    "price": 95500,
    "productOption": "(23%) 코튼허그+코튼브리즈(+46,500원)"
  },
  {
    "id": 25,
    "productCode": 6,
    "productName": "시그니처 퍼퓸 코튼허그",
    "productSelect": "[레이어링추천] 향수 세트",
    "price": 95500,
    "productOption": "(23%) 코튼허그+코튼딜라잇부케(+46,500원)"
  },
  {
    "id": 26,
    "productCode": 6,
    "productName": "시그니처 퍼퓸 코튼허그",
    "productSelect": "[레이어링추천] 향수 세트",
    "price": 88500,
    "productOption": "(26%) 코튼허그+코튼썩세스(+39,500원)"
  },
  {
    "id": 27,
    "productCode": 7,
    "productName": "시그니처 퍼퓸 코튼브리즈",
    "productSelect": "향수 단품",
    "price": 49000,
    "productOption": "코튼브리즈 1개"
  },
  {
    "id": 28,
    "productCode": 7,
    "productName": "시그니처 퍼퓸 코튼브리즈",
    "productSelect": "코튼브리즈 세트",
    "price": 69000,
    "productOption": "(29%) 향수+퍼퓸샤워(+20,000원)"
  },
  {
    "id": 29,
    "productCode": 7,
    "productName": "시그니처 퍼퓸 코튼브리즈",
    "productSelect": "[레이어링추천] 향수 세트",
    "price": 85900,
    "productOption": "(23%) 코튼브리즈+코튼허그(+36,900원)"
  },
  {
    "id": 30,
    "productCode": 7,
    "productName": "시그니처 퍼퓸 코튼브리즈",
    "productSelect": "[레이어링추천] 향수 세트",
    "price": 95900,
    "productOption": "(23%) 코튼브리즈+코튼메모리(+46,900원)"
  },
  {
    "id": 31,
    "productCode": 7,
    "productName": "시그니처 퍼퓸 코튼브리즈",
    "productSelect": "[레이어링추천] 향수 세트",
    "price": 95900,
    "productOption": "(23%) 코튼브리즈+코튼딜라잇부케(+46,900원)"
  },
  {
    "id": 32,
    "productCode": 7,
    "productName": "시그니처 퍼퓸 코튼브리즈",
    "productSelect": "[레이어링추천] 향수 세트",
    "price": 99000,
    "productOption": "(30%) 코튼브리즈+코튼썩세스(+50,000원)"
  },
  {
    "id": 33,
    "productCode": 8,
    "productName": "시그니처 퍼퓸 코튼메모리",
    "productSelect": "단품",
    "price": 49000,
    "productOption": "코튼메모리 1개"
  },
  {
    "id": 34,
    "productCode": 8,
    "productName": "시그니처 퍼퓸 코튼메모리",
    "productSelect": "코튼메모리 세트",
    "price": 65000,
    "productOption": "(24%) 퍼퓸+핸드크림(+16,000원)"
  },
  {
    "id": 35,
    "productCode": 8,
    "productName": "시그니처 퍼퓸 코튼메모리",
    "productSelect": "코튼메모리 세트",
    "price": 69000,
    "productOption": "(29%) 퍼퓸+퍼퓸샤워(+20,000원)"
  },
  {
    "id": 36,
    "productCode": 8,
    "productName": "시그니처 퍼퓸 코튼메모리",
    "productSelect": "코튼메모리 세트",
    "price": 69000,
    "productOption": "(29%) 퍼퓸+퍼퓸로션(+20,000원)"
  },
  {
    "id": 37,
    "productCode": 8,
    "productName": "시그니처 퍼퓸 코튼메모리",
    "productSelect": "코튼메모리 세트",
    "price": 89000,
    "productOption": "(33%) 퍼퓸+퍼퓸샤워+퍼퓸로션(+40,000원)"
  },
  {
    "id": 38,
    "productCode": 8,
    "productName": "시그니처 퍼퓸 코튼메모리",
    "productSelect": "[레이어링추천] 향수 세트",
    "price": 85900,
    "productOption": "(23%) 코튼메모리+코튼허그(+36,900원)"
  },
  {
    "id": 39,
    "productCode": 8,
    "productName": "시그니처 퍼퓸 코튼메모리",
    "productSelect": "[레이어링추천] 향수 세트",
    "price": 95900,
    "productOption": "(23%) 코튼메모리+코튼브리즈(+46,900원)"
  },
  {
    "id": 40,
    "productCode": 8,
    "productName": "시그니처 퍼퓸 코튼메모리",
    "productSelect": "[레이어링추천] 향수 세트",
    "price": 95900,
    "productOption": "(23%) 코튼메모리+코튼딜라잇부케(+46,900원)"
  },
  {
    "id": 41,
    "productCode": 9,
    "productName": "시그니처 퍼퓸 벨벳허그",
    "productSelect": "향수 단품",
    "price": 49000,
    "productOption": "벨벳허그"
  },
  {
    "id": 42,
    "productCode": 9,
    "productName": "시그니처 퍼퓸 벨벳허그",
    "productSelect": "미니어처 세트",
    "price": 59000,
    "productOption": "벨벳허그+미니어처 (+10,000원)"
  },
  {
    "id": 43,
    "productCode": 9,
    "productName": "시그니처 퍼퓸 벨벳허그",
    "productSelect": "[레이어링추천] 향수 세트",
    "price": 85900,
    "productOption": "벨벳허그 + 코튼키스 (+36,900원)"
  },
  {
    "id": 44,
    "productCode": 9,
    "productName": "시그니처 퍼퓸 벨벳허그",
    "productSelect": "[레이어링추천] 향수 세트",
    "price": 95900,
    "productOption": "벨벳허그+코튼디어나잇 (+46,900원)"
  },
  {
    "id": 45,
    "productCode": 9,
    "productName": "시그니처 퍼퓸 벨벳허그",
    "productSelect": "[레이어링추천] 향수 세트",
    "price": 95900,
    "productOption": "벨벳허그+코튼메모리 (+46,900원)"
  },
  {
    "id": 46,
    "productCode": 10,
    "productName": "시그니처 퍼퓸 코튼 디어 나잇",
    "productSelect": "[한정수량] 코튼 디어나잇 롤온기획세트",
    "price": 49000,
    "productOption": "기획세트 1개"
  },
  {
    "id": 47,
    "productCode": 10,
    "productName": "시그니처 퍼퓸 코튼 디어 나잇",
    "productSelect": "[EVENT/한정수량] 코튼디어나잇 세트",
    "price": 65000,
    "productOption": "(24%) 코튼 디어나잇 롤온기획세트+핸드크림 (+16,000원)"
  },
  {
    "id": 48,
    "productCode": 10,
    "productName": "시그니처 퍼퓸 코튼 디어 나잇",
    "productSelect": "[EVENT/한정수량] 코튼디어나잇 세트",
    "price": 69000,
    "productOption": "(29%) 코튼 디어나잇 롤온기획세트+퍼퓸샤워 (+20,000원)"
  },
  {
    "id": 49,
    "productCode": 10,
    "productName": "시그니처 퍼퓸 코튼 디어 나잇",
    "productSelect": "[레이어링추천] 향수 세트",
    "price": 85900,
    "productOption": "(23%) 코튼 디어나잇 롤온기획세트+코튼허그 (+36,900원)"
  },
  {
    "id": 50,
    "productCode": 10,
    "productName": "시그니처 퍼퓸 코튼 디어 나잇",
    "productSelect": "[레이어링추천] 향수 세트",
    "price": 95900,
    "productOption": "(23%) 코튼 디어나잇 롤온기획세트+코튼메모리 (+46,900원)"
  },
  {
    "id": 51,
    "productCode": 10,
    "productName": "시그니처 퍼퓸 코튼 디어 나잇",
    "productSelect": "[레이어링추천] 향수 세트",
    "price": 95900,
    "productOption": "(23%) 코튼 디어나잇 롤온기획세트+벨벳허그 (+46,900원)"
  },
  {
    "id": 52,
    "productCode": 11,
    "productName": "시그니처 솔리드 퍼퓸",
    "productSelect": "코튼허그",
    "price": 32000,
    "productOption": "코튼허그 단품"
  },
  {
    "id": 53,
    "productCode": 11,
    "productName": "시그니처 솔리드 퍼퓸",
    "productSelect": "코튼 메모리",
    "price": 32000,
    "productOption": "(공식몰 단독) 코튼메모리X미니레더백"
  },
  {
    "id": 54,
    "productCode": 11,
    "productName": "시그니처 솔리드 퍼퓸",
    "productSelect": "벨벳허그",
    "price": 32000,
    "productOption": "(공식몰 단독) 벨벳허그X미니레더백"
  },
  {
    "id": 55,
    "productCode": 12,
    "productName": "시그니처 솔리드 퍼퓸 코튼 허그",
    "productSelect": "단품",
    "price": 32000,
    "productOption": "코튼허그 단품"
  },
  {
    "id": 56,
    "productCode": 13,
    "productName": "시그니처 솔리드 퍼퓸 코튼 메모리",
    "productSelect": "단품",
    "price": 32000,
    "productOption": "(공식몰 단독) 코튼메모리X미니레더백"
  },
  {
    "id": 57,
    "productCode": 14,
    "productName": "시그니처 솔리드 퍼퓸 벨벳 허그",
    "productSelect": "단품",
    "price": 32000,
    "productOption": "(공식몰 단독) 벨벳허그X미니레더백"
  },
  {
    "id": 58,
    "productCode": 15,
    "productName": "퍼퓸 코튼 메모리 핸드크림 세트",
    "productSelect": "코튼 메모리 핸드크림 세트",
    "price": 27000,
    "productOption": "코튼메모리 핸드크림 + 퍼퓸"
  },
  {
    "id": 59,
    "productCode": 16,
    "productName": "퍼퓸 샤워 기프트 세트",
    "productSelect": "코튼허그",
    "price": 19000,
    "productOption": "HAPPY BIRTHDAY"
  },
  {
    "id": 60,
    "productCode": 16,
    "productName": "퍼퓸 샤워 기프트 세트",
    "productSelect": "코튼허그",
    "price": 19000,
    "productOption": "THANK YOU"
  },
  {
    "id": 61,
    "productCode": 16,
    "productName": "퍼퓸 샤워 기프트 세트",
    "productSelect": "코튼허그",
    "price": 19000,
    "productOption": "LOVE YOU"
  },
  {
    "id": 62,
    "productCode": 16,
    "productName": "퍼퓸 샤워 기프트 세트",
    "productSelect": "코튼메모리",
    "price": 19000,
    "productOption": "HAPPY BIRTHDAY"
  },
  {
    "id": 63,
    "productCode": 16,
    "productName": "퍼퓸 샤워 기프트 세트",
    "productSelect": "코튼메모리",
    "price": 19000,
    "productOption": "THANK YOU"
  },
  {
    "id": 64,
    "productCode": 16,
    "productName": "퍼퓸 샤워 기프트 세트",
    "productSelect": "코튼메모리",
    "price": 19000,
    "productOption": "LOVE YOU"
  },
  {
    "id": 65,
    "productCode": 17,
    "productName": "올인원 퍼퓸 샤워",
    "productSelect": "코튼허그",
    "price": 24000,
    "productOption": "퍼퓸샤워 1개"
  },
  {
    "id": 66,
    "productCode": 17,
    "productName": "올인원 퍼퓸 샤워",
    "productSelect": "코튼허그",
    "price": 45000,
    "productOption": "(36%) 퍼퓸샤워 2개 (+21,000원)"
  },
  {
    "id": 67,
    "productCode": 17,
    "productName": "올인원 퍼퓸 샤워",
    "productSelect": "코튼허그",
    "price": 45000,
    "productOption": "(36%) 퍼퓸샤워+퍼퓸로션 (+21,000원)"
  },
  {
    "id": 68,
    "productCode": 17,
    "productName": "올인원 퍼퓸 샤워",
    "productSelect": "코튼허그",
    "price": 59000,
    "productOption": "(30%) 퍼퓸샤워+퍼퓸 (+35,000원)"
  },
  {
    "id": 69,
    "productCode": 17,
    "productName": "올인원 퍼퓸 샤워",
    "productSelect": "코튼키스",
    "price": 24000,
    "productOption": "퍼퓸샤워 1개"
  },
  {
    "id": 70,
    "productCode": 17,
    "productName": "올인원 퍼퓸 샤워",
    "productSelect": "코튼키스",
    "price": 45000,
    "productOption": "(36%) 퍼퓸샤워 2개 (+21,000원)"
  },
  {
    "id": 71,
    "productCode": 17,
    "productName": "올인원 퍼퓸 샤워",
    "productSelect": "코튼키스",
    "price": 45000,
    "productOption": "(36%) 퍼퓸샤워+퍼퓸로션 (+21,000원)"
  },
  {
    "id": 72,
    "productCode": 17,
    "productName": "올인원 퍼퓸 샤워",
    "productSelect": "코튼키스",
    "price": 59000,
    "productOption": "(30%) 퍼퓸샤워+퍼퓸 (+35,000원)"
  },
  {
    "id": 73,
    "productCode": 17,
    "productName": "올인원 퍼퓸 샤워",
    "productSelect": "코튼메모리",
    "price": 24000,
    "productOption": "퍼퓸샤워 1개"
  },
  {
    "id": 74,
    "productCode": 17,
    "productName": "올인원 퍼퓸 샤워",
    "productSelect": "코튼메모리",
    "price": 45000,
    "productOption": "(36%) 퍼퓸샤워 2개 (+21,000원)"
  },
  {
    "id": 75,
    "productCode": 17,
    "productName": "올인원 퍼퓸 샤워",
    "productSelect": "코튼메모리",
    "price": 45000,
    "productOption": "(36%) 퍼퓸샤워+퍼퓸로션 (+21,000원)"
  },
  {
    "id": 76,
    "productCode": 17,
    "productName": "올인원 퍼퓸 샤워",
    "productSelect": "코튼메모리",
    "price": 69000,
    "productOption": "(29%) 퍼퓸샤워+퍼퓸 (+45,000원)"
  },
  {
    "id": 77,
    "productCode": 17,
    "productName": "올인원 퍼퓸 샤워",
    "productSelect": "코튼브리즈",
    "price": 24000,
    "productOption": "퍼퓸샤워 1개"
  },
  {
    "id": 78,
    "productCode": 17,
    "productName": "올인원 퍼퓸 샤워",
    "productSelect": "코튼브리즈",
    "price": 45000,
    "productOption": "(36%) 퍼퓸샤워 2개 (+21,000원)"
  },
  {
    "id": 79,
    "productCode": 17,
    "productName": "올인원 퍼퓸 샤워",
    "productSelect": "코튼브리즈",
    "price": 69000,
    "productOption": "(29%) 퍼퓸샤워+퍼퓸 (+45,000원)"
  },
  {
    "id": 80,
    "productCode": 17,
    "productName": "올인원 퍼퓸 샤워",
    "productSelect": "코튼썩세스",
    "price": 24000,
    "productOption": "퍼퓸샤워 1개"
  },
  {
    "id": 81,
    "productCode": 17,
    "productName": "올인원 퍼퓸 샤워",
    "productSelect": "코튼썩세스",
    "price": 45000,
    "productOption": "(36%) 퍼퓸샤워 2개 (+21,000원)"
  },
  {
    "id": 82,
    "productCode": 17,
    "productName": "올인원 퍼퓸 샤워",
    "productSelect": "코튼썩세스",
    "price": 69000,
    "productOption": "(29%) 퍼퓸샤워+퍼퓸 (+45,000원)"
  },
  {
    "id": 83,
    "productCode": 17,
    "productName": "올인원 퍼퓸 샤워",
    "productSelect": "코튼디어나잇",
    "price": 24000,
    "productOption": "퍼퓸샤워 1개"
  },
  {
    "id": 84,
    "productCode": 17,
    "productName": "올인원 퍼퓸 샤워",
    "productSelect": "코튼디어나잇",
    "price": 45000,
    "productOption": "(36%) 퍼퓸샤워 2개 (+21,000원)"
  },
  {
    "id": 85,
    "productCode": 17,
    "productName": "올인원 퍼퓸 샤워",
    "productSelect": "코튼디어나잇",
    "price": 69000,
    "productOption": "(29%) 퍼퓸샤워+퍼퓸 (+45,000원)"
  },
  {
    "id": 86,
    "productCode": 17,
    "productName": "올인원 퍼퓸 샤워",
    "productSelect": "코튼딜라잇부케",
    "price": 24000,
    "productOption": "퍼퓸샤워 1개"
  },
  {
    "id": 87,
    "productCode": 17,
    "productName": "올인원 퍼퓸 샤워",
    "productSelect": "코튼딜라잇부케",
    "price": 45000,
    "productOption": "(36%) 퍼퓸샤워 2개 (+21,000원)"
  },
  {
    "id": 88,
    "productCode": 17,
    "productName": "올인원 퍼퓸 샤워",
    "productSelect": "코튼딜라잇부케",
    "price": 69000,
    "productOption": "(29%) 퍼퓸샤워+퍼퓸 (+45,000원)"
  },
  {
    "id": 89,
    "productCode": 17,
    "productName": "올인원 퍼퓸 샤워",
    "productSelect": "바질테라스",
    "price": 24000,
    "productOption": "퍼퓸샤워 1개"
  },
  {
    "id": 90,
    "productCode": 17,
    "productName": "올인원 퍼퓸 샤워",
    "productSelect": "바질테라스",
    "price": 45000,
    "productOption": "(36%) 퍼퓸샤워 2개 (+21,000원)"
  },
  {
    "id": 91,
    "productCode": 17,
    "productName": "올인원 퍼퓸 샤워",
    "productSelect": "바질테라스",
    "price": 69000,
    "productOption": "(29%) 퍼퓸샤워+퍼퓸 (+45,000원)"
  },
  {
    "id": 92,
    "productCode": 18,
    "productName": "올인원 퍼퓸 샤워 코튼키스",
    "productSelect": "코튼키스 퍼퓸샤워 단품",
    "price": 24000,
    "productOption": "퍼퓸샤워 1개"
  },
  {
    "id": 93,
    "productCode": 18,
    "productName": "올인원 퍼퓸 샤워 코튼키스",
    "productSelect": "코튼키스 퍼퓸샤워 단품",
    "price": 45000,
    "productOption": "(36%) 퍼퓸샤워 2개 (+21,000원)"
  },
  {
    "id": 94,
    "productCode": 18,
    "productName": "올인원 퍼퓸 샤워 코튼키스",
    "productSelect": "코튼키스 퍼퓸샤워 세트",
    "price": 45000,
    "productOption": "(36%) 퍼퓸샤워+퍼퓸로션 (+21,000원)"
  },
  {
    "id": 95,
    "productCode": 18,
    "productName": "올인원 퍼퓸 샤워 코튼키스",
    "productSelect": "코튼키스 퍼퓸샤워 세트",
    "price": 59000,
    "productOption": "(30%) 퍼퓸샤워+퍼퓸 (+35,000원)"
  },
  {
    "id": 96,
    "productCode": 19,
    "productName": "퍼퓸 샤워 코튼 메모리",
    "productSelect": "코튼메모리 퍼퓸샤워 단품",
    "price": 24000,
    "productOption": "퍼퓸샤워 1개"
  },
  {
    "id": 97,
    "productCode": 19,
    "productName": "퍼퓸 샤워 코튼 메모리",
    "productSelect": "코튼메모리 퍼퓸샤워 단품",
    "price": 45000,
    "productOption": "(36%) 퍼퓸샤워 2개 (+21,000원)"
  },
  {
    "id": 98,
    "productCode": 19,
    "productName": "퍼퓸 샤워 코튼 메모리",
    "productSelect": "코튼메모리 퍼퓸샤워 세트",
    "price": 45000,
    "productOption": "(36%) 퍼퓸샤워+퍼퓸로션 (+21,000원)"
  },
  {
    "id": 99,
    "productCode": 19,
    "productName": "퍼퓸 샤워 코튼 메모리",
    "productSelect": "코튼메모리 퍼퓸샤워 세트",
    "price": 49000,
    "productOption": "(33%) 퍼퓸샤워+퍼퓸샴푸 (+25,000원)"
  },
  {
    "id": 100,
    "productCode": 19,
    "productName": "퍼퓸 샤워 코튼 메모리",
    "productSelect": "코튼메모리 퍼퓸샤워 세트",
    "price": 69000,
    "productOption": "(29%) 퍼퓸샤워+퍼퓸 (+45,000원)"
  },
  {
    "id": 101,
    "productCode": 19,
    "productName": "퍼퓸 샤워 코튼 메모리",
    "productSelect": "코튼메모리 퍼퓸샤워 세트",
    "price": 89000,
    "productOption": "(33%) 퍼퓸샤워+퍼퓸로션+퍼퓸 (+65,000원)"
  },
  {
    "id": 102,
    "productCode": 20,
    "productName": "퍼퓸 샤워 코튼 디어 나잇",
    "productSelect": "코튼디어나잇 퍼퓸샤워 단품",
    "price": 24000,
    "productOption": "퍼퓸샤워 1개"
  },
  {
    "id": 103,
    "productCode": 20,
    "productName": "퍼퓸 샤워 코튼 디어 나잇",
    "productSelect": "코튼디어나잇 퍼퓸샤워 단품",
    "price": 45000,
    "productOption": "(36%) 퍼퓸샤워 2개 (+21,000원)"
  },
  {
    "id": 104,
    "productCode": 20,
    "productName": "퍼퓸 샤워 코튼 디어 나잇",
    "productSelect": "코튼디어나잇 퍼퓸샤워 세트",
    "price": 69000,
    "productOption": "(29%) 퍼퓸샤워+퍼퓸 (+45,000원)"
  },
  {
    "id": 105,
    "productCode": 21,
    "productName": "퍼퓸 샤워 코튼 브리즈",
    "productSelect": "코튼 브리즈 퍼퓸샤워 단품",
    "price": 24000,
    "productOption": "퍼퓸샤워 1개"
  },
  {
    "id": 106,
    "productCode": 21,
    "productName": "퍼퓸 샤워 코튼 브리즈",
    "productSelect": "코튼 브리즈 퍼퓸샤워 단품",
    "price": 45000,
    "productOption": "(36%) 퍼퓸샤워 2개 (+21,000원)"
  },
  {
    "id": 107,
    "productCode": 21,
    "productName": "퍼퓸 샤워 코튼 브리즈",
    "productSelect": "퍼퓸 샤워 코튼 브리즈 퍼퓸샤워 세트",
    "price": 69000,
    "productOption": "(29%) 퍼퓸샤워+퍼퓸 (+45,000원)"
  },
  {
    "id": 108,
    "productCode": 22,
    "productName": "올인원 퍼퓸 샤워 코튼 썩세스",
    "productSelect": "코튼 썩세스 퍼퓸샤워 단품",
    "price": 24000,
    "productOption": "퍼퓸샤워 1개"
  },
  {
    "id": 109,
    "productCode": 22,
    "productName": "올인원 퍼퓸 샤워 코튼 썩세스",
    "productSelect": "코튼 썩세스 퍼퓸샤워 단품",
    "price": 45000,
    "productOption": "(36%) 퍼퓸샤워 2개 (+21,000원)"
  },
  {
    "id": 110,
    "productCode": 22,
    "productName": "올인원 퍼퓸 샤워 코튼 썩세스",
    "productSelect": "코튼 썩세스 퍼퓸샤워 세트",
    "price": 69000,
    "productOption": "(29%) 퍼퓸샤워+퍼퓸 (+45,000원)"
  },
  {
    "id": 111,
    "productCode": 23,
    "productName": "올인원 퍼퓸 샤워 코튼허그",
    "productSelect": "코튼허그 퍼퓸샤워 단품",
    "price": 24000,
    "productOption": "퍼퓸샤워 1개"
  },
  {
    "id": 112,
    "productCode": 23,
    "productName": "올인원 퍼퓸 샤워 코튼허그",
    "productSelect": "코튼허그 퍼퓸샤워 단품",
    "price": 45000,
    "productOption": "(36%) 퍼퓸샤워 2개 (+21,000원)"
  },
  {
    "id": 113,
    "productCode": 23,
    "productName": "올인원 퍼퓸 샤워 코튼허그",
    "productSelect": "코튼허그 퍼퓸샤워 세트",
    "price": 45000,
    "productOption": "(36%) 퍼퓸샤워+퍼퓸로션 (+21,000원)"
  },
  {
    "id": 114,
    "productCode": 23,
    "productName": "올인원 퍼퓸 샤워 코튼허그",
    "productSelect": "코튼허그 퍼퓸샤워 세트",
    "price": 59000,
    "productOption": "(30%) 퍼퓸샤워+퍼퓸 (+35,000원)"
  },
  {
    "id": 115,
    "productCode": 24,
    "productName": "퍼퓸 샤워 코튼 딜라잇 부케",
    "productSelect": "코튼 딜라잇 부케 단품",
    "price": 24000,
    "productOption": "퍼퓸샤워 1개"
  },
  {
    "id": 116,
    "productCode": 24,
    "productName": "퍼퓸 샤워 코튼 딜라잇 부케",
    "productSelect": "코튼 딜라잇 부케 단품",
    "price": 45000,
    "productOption": "(36%) 퍼퓸샤워 2개 (+21,000원)"
  },
  {
    "id": 117,
    "productCode": 24,
    "productName": "퍼퓸 샤워 코튼 딜라잇 부케",
    "productSelect": "코튼 딜라잇 부케 세트",
    "price": 69000,
    "productOption": "(29%) 퍼퓸샤워+퍼퓸 (+45,000원)"
  },
  {
    "id": 118,
    "productCode": 25,
    "productName": "시그니처 퍼퓸",
    "productSelect": "코튼 허그",
    "price": 39000,
    "productOption": "퍼퓸"
  },
  {
    "id": 119,
    "productCode": 25,
    "productName": "시그니처 퍼퓸",
    "productSelect": "코튼 허그",
    "price": 59000,
    "productOption": "(30%) 퍼퓸+퍼퓸샤워 (+20,000원)"
  },
  {
    "id": 120,
    "productCode": 25,
    "productName": "시그니처 퍼퓸",
    "productSelect": "코튼 허그",
    "price": 59000,
    "productOption": "(30%) 퍼퓸+퍼퓸로션 (+20,000원)"
  },
  {
    "id": 121,
    "productCode": 25,
    "productName": "시그니처 퍼퓸",
    "productSelect": "코튼키스",
    "price": 39000,
    "productOption": "퍼퓸"
  },
  {
    "id": 122,
    "productCode": 25,
    "productName": "시그니처 퍼퓸",
    "productSelect": "코튼썩세스",
    "price": 49000,
    "productOption": "퍼퓸 (+10,000원)"
  },
  {
    "id": 123,
    "productCode": 25,
    "productName": "시그니처 퍼퓸",
    "productSelect": "코튼썩세스",
    "price": 69000,
    "productOption": "(30%) 퍼퓸+퍼퓸로션 (+30,000원)"
  },
  {
    "id": 124,
    "productCode": 25,
    "productName": "시그니처 퍼퓸",
    "productSelect": "코튼메모리",
    "price": 49000,
    "productOption": "퍼퓸 (+10,000원)"
  },
  {
    "id": 125,
    "productCode": 25,
    "productName": "시그니처 퍼퓸",
    "productSelect": "코튼메모리",
    "price": 69000,
    "productOption": "(29%) 퍼퓸+퍼퓸샤워 (+30,000원)"
  },
  {
    "id": 126,
    "productCode": 25,
    "productName": "시그니처 퍼퓸",
    "productSelect": "코튼메모리",
    "price": 69000,
    "productOption": "(29%) 퍼퓸+퍼퓸로션 (+30,000원)"
  },
  {
    "id": 127,
    "productCode": 25,
    "productName": "시그니처 퍼퓸",
    "productSelect": "코튼브리즈",
    "price": 49000,
    "productOption": "퍼퓸 (+10,000원)"
  },
  {
    "id": 128,
    "productCode": 25,
    "productName": "시그니처 퍼퓸",
    "productSelect": "코튼브리즈",
    "price": 69000,
    "productOption": "(29%) 퍼퓸+퍼퓸샤워 (+30,000원)"
  },
  {
    "id": 129,
    "productCode": 25,
    "productName": "시그니처 퍼퓸",
    "productSelect": "[FW시즌한정] 코튼 디어나잇 롤온 기획",
    "price": 49000,
    "productOption": "퍼퓸 (+10,000원)"
  },
  {
    "id": 130,
    "productCode": 25,
    "productName": "시그니처 퍼퓸",
    "productSelect": "[FW시즌한정] 코튼 디어나잇 롤온 기획",
    "price": 69000,
    "productOption": "(29%) 퍼퓸+퍼퓸샤워 (+30,000원)"
  },
  {
    "id": 131,
    "productCode": 25,
    "productName": "시그니처 퍼퓸",
    "productSelect": "코튼딜라잇부케",
    "price": 49000,
    "productOption": "퍼퓸 (+10,000원)"
  },
  {
    "id": 132,
    "productCode": 25,
    "productName": "시그니처 퍼퓸",
    "productSelect": "코튼딜라잇부케",
    "price": 69000,
    "productOption": "(29%) 퍼퓸+퍼퓸샤워 (+30,000원)"
  },
  {
    "id": 133,
    "productCode": 25,
    "productName": "시그니처 퍼퓸",
    "productSelect": "벨벳허그",
    "price": 49000,
    "productOption": "퍼퓸 (+10,000원)"
  },
  {
    "id": 134,
    "productCode": 25,
    "productName": "시그니처 퍼퓸",
    "productSelect": "바질테라스",
    "price": 49000,
    "productOption": "퍼퓸 (+10,000원)"
  },
  {
    "id": 135,
    "productCode": 25,
    "productName": "시그니처 퍼퓸",
    "productSelect": "피그누아",
    "price": 68000,
    "productOption": "(29%) 퍼퓸+퍼퓸샤워 (+29,000원)"
  },
  {
    "id": 136,
    "productCode": 25,
    "productName": "시그니처 퍼퓸",
    "productSelect": "피그누아",
    "price": 49000,
    "productOption": "퍼퓸 (+10,000원)"
  },
  {
    "id": 137,
    "productCode": 25,
    "productName": "시그니처 퍼퓸",
    "productSelect": "상탈레인",
    "price": 49000,
    "productOption": "퍼퓸 (+10,000원)"
  },
  {
    "id": 138,
    "productCode": 25,
    "productName": "시그니처 퍼퓸",
    "productSelect": "[레이어링추천] 코튼 컬렉션",
    "price": 75900,
    "productOption": "(23%) 코튼허그+코튼키스 (+36,900원)"
  },
  {
    "id": 139,
    "productCode": 25,
    "productName": "시그니처 퍼퓸",
    "productSelect": "[레이어링추천] 코튼 컬렉션",
    "price": 85900,
    "productOption": "(23%) 코튼허그+코튼메모리 (+46,900원)"
  },
  {
    "id": 140,
    "productCode": 25,
    "productName": "시그니처 퍼퓸",
    "productSelect": "[레이어링추천] 코튼 컬렉션",
    "price": 85900,
    "productOption": "(23%) 코튼허그+코튼디어나잇 롤온 기획 (+46,900원)"
  },
  {
    "id": 141,
    "productCode": 25,
    "productName": "시그니처 퍼퓸",
    "productSelect": "[레이어링추천] 코튼 컬렉션",
    "price": 85900,
    "productOption": "(23%) 코튼허그+코튼브리즈 (+46,900원)"
  },
  {
    "id": 142,
    "productCode": 25,
    "productName": "시그니처 퍼퓸",
    "productSelect": "[레이어링추천] 코튼 컬렉션",
    "price": 85900,
    "productOption": "(23%) 코튼허그+코튼딜라잇부케 (+46,900원)"
  },
  {
    "id": 143,
    "productCode": 25,
    "productName": "시그니처 퍼퓸",
    "productSelect": "[레이어링추천] 코튼 컬렉션",
    "price": 95900,
    "productOption": "(23%) 코튼메모리+코튼딜라잇부케 (+56,900원)"
  },
  {
    "id": 144,
    "productCode": 25,
    "productName": "시그니처 퍼퓸",
    "productSelect": "[레이어링추천] 코튼 컬렉션",
    "price": 95900,
    "productOption": "(23%) 코튼메모리+코튼디어나잇 롤온 기획 (+56,900원)"
  },
  {
    "id": 145,
    "productCode": 25,
    "productName": "시그니처 퍼퓸",
    "productSelect": "[레이어링추천] 코튼 컬렉션",
    "price": 95900,
    "productOption": "(23%) 코튼브리즈+코튼딜라잇부케 (+56,900원)"
  },
  {
    "id": 146,
    "productCode": 25,
    "productName": "시그니처 퍼퓸",
    "productSelect": "[레이어링추천] 코튼 컬렉션",
    "price": 85900,
    "productOption": "(26%) 코튼허그+코튼썩세스 (+46,900원)"
  },
  {
    "id": 147,
    "productCode": 25,
    "productName": "시그니처 퍼퓸",
    "productSelect": "[레이어링추천] 코튼 컬렉션",
    "price": 95900,
    "productOption": "(23%) 벨벳허그+코튼디어나잇 롤온 기획 (+56,900원)"
  },
  {
    "id": 148,
    "productCode": 25,
    "productName": "시그니처 퍼퓸",
    "productSelect": "[레이어링추천] 코튼 컬렉션",
    "price": 95900,
    "productOption": "(23%) 벨벳허그+코튼메모리 (+56,900원)"
  },
  {
    "id": 149,
    "productCode": 25,
    "productName": "시그니처 퍼퓸",
    "productSelect": "[EVENT] 내추럴 컬렉션",
    "price": 98000,
    "productOption": "피그누아+바질테라스 (+상탈레인 9ml/스톤디퓨저 증정) (+59,000원)"
  },
  {
    "id": 150,
    "productCode": 25,
    "productName": "시그니처 퍼퓸",
    "productSelect": "[EVENT] 내추럴 컬렉션",
    "price": 98000,
    "productOption": "상탈레인+피그누아 (+상탈레인 9ml/스톤디퓨저 증정) (+59,000원)"
  },
  {
    "id": 151,
    "productCode": 25,
    "productName": "시그니처 퍼퓸",
    "productSelect": "[EVENT] 내추럴 컬렉션",
    "price": 98000,
    "productOption": "상탈레인+바질테라스 (+상탈레인 9ml/스톤디퓨저 증정) (+59,000원)"
  },
  {
    "id": 152,
    "productCode": 26,
    "productName": "퍼퓸 바디로션",
    "productSelect": "코튼 허그",
    "price": 24000,
    "productOption": "바디로션"
  },
  {
    "id": 153,
    "productCode": 26,
    "productName": "퍼퓸 바디로션",
    "productSelect": "코튼 허그",
    "price": 45000,
    "productOption": "(36%) 퍼퓸로션+퍼퓸샤워 (+21,000원)"
  },
  {
    "id": 154,
    "productCode": 26,
    "productName": "퍼퓸 바디로션",
    "productSelect": "코튼 허그",
    "price": 59000,
    "productOption": "(30%) 퍼퓸로션+퍼퓸 (+35,000원)"
  },
  {
    "id": 155,
    "productCode": 26,
    "productName": "퍼퓸 바디로션",
    "productSelect": "코튼키스",
    "price": 24000,
    "productOption": "바디로션"
  },
  {
    "id": 156,
    "productCode": 26,
    "productName": "퍼퓸 바디로션",
    "productSelect": "코튼키스",
    "price": 45000,
    "productOption": "(36%) 퍼퓸로션+퍼퓸샤워 (+21,000원)"
  },
  {
    "id": 157,
    "productCode": 26,
    "productName": "퍼퓸 바디로션",
    "productSelect": "코튼키스",
    "price": 59000,
    "productOption": "(30%) 퍼퓸로션+퍼퓸 (+35,000원)"
  },
  {
    "id": 158,
    "productCode": 26,
    "productName": "퍼퓸 바디로션",
    "productSelect": "코튼썩세스",
    "price": 24000,
    "productOption": "바디로션"
  },
  {
    "id": 159,
    "productCode": 26,
    "productName": "퍼퓸 바디로션",
    "productSelect": "코튼썩세스",
    "price": 45000,
    "productOption": "(36%) 퍼퓸로션+퍼퓸샤워 (+21,000원)"
  },
  {
    "id": 160,
    "productCode": 26,
    "productName": "퍼퓸 바디로션",
    "productSelect": "코튼썩세스",
    "price": 63000,
    "productOption": "(30%) 퍼퓸로션+퍼퓸 (+39,000원)"
  },
  {
    "id": 161,
    "productCode": 26,
    "productName": "퍼퓸 바디로션",
    "productSelect": "코튼메모리",
    "price": 24000,
    "productOption": "바디로션"
  },
  {
    "id": 162,
    "productCode": 26,
    "productName": "퍼퓸 바디로션",
    "productSelect": "코튼메모리",
    "price": 45000,
    "productOption": "(36%) 퍼퓸로션+퍼퓸샤워 (+21,000원)"
  },
  {
    "id": 163,
    "productCode": 26,
    "productName": "퍼퓸 바디로션",
    "productSelect": "코튼메모리",
    "price": 69000,
    "productOption": "(29%) 퍼퓸로션+퍼퓸 (+45,000원)"
  },
  {
    "id": 164,
    "productCode": 27,
    "productName": "퍼퓸 바디로션 코튼 메모리",
    "productSelect": "코튼메모리 바디로션",
    "price": 24000,
    "productOption": "바디로션"
  },
  {
    "id": 165,
    "productCode": 27,
    "productName": "퍼퓸 바디로션 코튼 메모리",
    "productSelect": "코튼메모리 퍼퓸로션 세트",
    "price": 45000,
    "productOption": "(36%) 퍼퓸로션+퍼퓸샤워 (+21,000원)"
  },
  {
    "id": 166,
    "productCode": 27,
    "productName": "퍼퓸 바디로션 코튼 메모리",
    "productSelect": "코튼메모리 퍼퓸로션 세트",
    "price": 69000,
    "productOption": "(29%) 퍼퓸로션+퍼퓸 (+45,000원)"
  },
  {
    "id": 167,
    "productCode": 27,
    "productName": "퍼퓸 바디로션 코튼 메모리",
    "productSelect": "코튼메모리 퍼퓸로션 세트",
    "price": 89000,
    "productOption": "(33%) 퍼퓸로션+퍼퓸샤워+퍼퓸 (+65,000원)"
  },
  {
    "id": 168,
    "productCode": 28,
    "productName": "퍼퓸 바디로션 코튼썩세스",
    "productSelect": "코튼 썩세스 바디로션",
    "price": 24000,
    "productOption": "바디로션"
  },
  {
    "id": 169,
    "productCode": 28,
    "productName": "퍼퓸 바디로션 코튼썩세스",
    "productSelect": "코튼 썩세스 바디로션",
    "price": 45000,
    "productOption": "(36%) 퍼퓸로션+퍼퓸샤워 (+21,000원)"
  },
  {
    "id": 170,
    "productCode": 28,
    "productName": "퍼퓸 바디로션 코튼썩세스",
    "productSelect": "코튼 썩세스 바디로션",
    "price": 63000,
    "productOption": "(30%) 퍼퓸로션+퍼퓸 (+39,000원)"
  },
  {
    "id": 171,
    "productCode": 29,
    "productName": "퍼퓸 바디로션 코튼허그",
    "productSelect": "코튼허그 바디로션",
    "price": 24000,
    "productOption": "바디로션"
  },
  {
    "id": 172,
    "productCode": 29,
    "productName": "퍼퓸 바디로션 코튼허그",
    "productSelect": "코튼허그 바디로션",
    "price": 45000,
    "productOption": "(36%) 퍼퓸로션+퍼퓸샤워 (+21,000원)"
  },
  {
    "id": 173,
    "productCode": 29,
    "productName": "퍼퓸 바디로션 코튼허그",
    "productSelect": "코튼허그 바디로션",
    "price": 59000,
    "productOption": "(30%) 퍼퓸로션+퍼퓸 (+35,000원)"
  },
  {
    "id": 174,
    "productCode": 30,
    "productName": "시그니처 퍼퓸 코튼 딜라잇부케",
    "productSelect": "향수 단품",
    "price": 49000,
    "productOption": "코튼 딜라잇부케 1개"
  },
  {
    "id": 175,
    "productCode": 30,
    "productName": "시그니처 퍼퓸 코튼 딜라잇부케",
    "productSelect": "코튼딜라잇부케 세트",
    "price": 69000,
    "productOption": "(29% OFF) 퍼퓸+ 퍼퓸샤워 (+20,000원)"
  },
  {
    "id": 176,
    "productCode": 30,
    "productName": "시그니처 퍼퓸 코튼 딜라잇부케",
    "productSelect": "[레이어링 추천] 향수 세트",
    "price": 85900,
    "productOption": "(23%) 딜라잇부케+코튼허그 (+36,900원)"
  },
  {
    "id": 177,
    "productCode": 30,
    "productName": "시그니처 퍼퓸 코튼 딜라잇부케",
    "productSelect": "[레이어링 추천] 향수 세트",
    "price": 95900,
    "productOption": "(23%) 딜라잇부케+코튼메모리 (+46,900원)"
  },
  {
    "id": 178,
    "productCode": 30,
    "productName": "시그니처 퍼퓸 코튼 딜라잇부케",
    "productSelect": "[레이어링 추천] 향수 세트",
    "price": 95900,
    "productOption": "(23%) 딜라잇부케+코튼브리즈 (+46,900원)"
  },
  {
    "id": 179,
    "productCode": 30,
    "productName": "시그니처 퍼퓸 코튼 딜라잇부케",
    "productSelect": "[레이어링 추천] 향수 세트",
    "price": 99000,
    "productOption": "(30%) 딜라잇부케+코튼썩세스 (+50,000원)"
  },
  {
    "id": 180,
    "productCode": 31,
    "productName": "시그니처 퍼퓸 코튼키스",
    "productSelect": "향수 단품",
    "price": 39000,
    "productOption": "코튼키스 1개"
  },
  {
    "id": 181,
    "productCode": 31,
    "productName": "시그니처 퍼퓸 코튼키스",
    "productSelect": "코튼키스 세트",
    "price": 55000,
    "productOption": "(25%) 퍼퓸+핸드크림(+16,000원)"
  },
  {
    "id": 182,
    "productCode": 31,
    "productName": "시그니처 퍼퓸 코튼키스",
    "productSelect": "코튼키스 세트",
    "price": 59000,
    "productOption": "(30%) 퍼퓸+퍼퓸샤워(+20,000원)"
  },
  {
    "id": 183,
    "productCode": 31,
    "productName": "시그니처 퍼퓸 코튼키스",
    "productSelect": "코튼키스 세트",
    "price": 59000,
    "productOption": "(30%) 퍼퓸+퍼퓸로션(+20,000원)"
  },
  {
    "id": 184,
    "productCode": 31,
    "productName": "시그니처 퍼퓸 코튼키스",
    "productSelect": "[레이어링 추천] 향수 세트",
    "price": 75900,
    "productOption": "(23%) 코튼키스+코튼허그 (+36,900원)"
  },
  {
    "id": 185,
    "productCode": 31,
    "productName": "시그니처 퍼퓸 코튼키스",
    "productSelect": "[레이어링 추천] 향수 세트",
    "price": 85900,
    "productOption": "(23%) 코튼키스+벨벳허그 (+46,900원)"
  },
  {
    "id": 186,
    "productCode": 31,
    "productName": "시그니처 퍼퓸 코튼키스",
    "productSelect": "[레이어링 추천] 향수 세트",
    "price": 94900,
    "productOption": "(26%) 코튼키스+코튼썩세스 (+55,900원)"
  },
  {
    "id": 187,
    "productCode": 32,
    "productName": "시그니처 퍼퓸 섬유유연제 코튼 허그",
    "productSelect": "섬유유연제 코튼 허그",
    "price": 12900,
    "productOption": "허그 1개"
  },
  {
    "id": 188,
    "productCode": 32,
    "productName": "시그니처 퍼퓸 섬유유연제 코튼 허그",
    "productSelect": "섬유유연제 코튼 허그",
    "price": 22900,
    "productOption": "허그 2개 (+10,000원)"
  },
  {
    "id": 189,
    "productCode": 32,
    "productName": "시그니처 퍼퓸 섬유유연제 코튼 허그",
    "productSelect": "섬유유연제 코튼 허그",
    "price": 38700,
    "productOption": "허그 3+1개 (+25,800원)"
  },
  {
    "id": 190,
    "productCode": 33,
    "productName": "비어틴 퍼퓸 샴푸 코튼 허그",
    "productSelect": "퍼퓸 샴푸 코튼 허그",
    "price": 25000,
    "productOption": "퍼퓸샴푸 1개 (+헤어토닉 증정)"
  },
  {
    "id": 191,
    "productCode": 33,
    "productName": "비어틴 퍼퓸 샴푸 코튼 허그",
    "productSelect": "퍼퓸 샴푸 코튼 허그",
    "price": 46000,
    "productOption": "퍼퓸샴푸 + 퍼퓸샤워 (+헤어토닉 증정) (+21,000원)"
  },
  {
    "id": 192,
    "productCode": 34,
    "productName": "리페어 퍼퓸 샴푸 코튼 메모리",
    "productSelect": "퍼퓸 샴푸 코튼 메모리",
    "price": 28000,
    "productOption": "퍼퓸 샴푸 1개"
  },
  {
    "id": 193,
    "productCode": 34,
    "productName": "리페어 퍼퓸 샴푸 코튼 메모리",
    "productSelect": "퍼퓸 샴푸 코튼 메모리",
    "price": 53500,
    "productOption": "(30%) 퍼퓸샴푸 2개 (+25,500원)"
  },
  {
    "id": 194,
    "productCode": 34,
    "productName": "리페어 퍼퓸 샴푸 코튼 메모리",
    "productSelect": "퍼퓸 샴푸 코튼 메모리",
    "price": 43500,
    "productOption": "(30%) 퍼퓸샴푸+트리트먼트 (+15,500원)"
  },
  {
    "id": 195,
    "productCode": 34,
    "productName": "리페어 퍼퓸 샴푸 코튼 메모리",
    "productSelect": "퍼퓸 샴푸 코튼 메모리",
    "price": 49000,
    "productOption": "(33%) 퍼퓸샴푸+퍼퓸샤워 (+21,000원)"
  },
  {
    "id": 196,
    "productCode": 34,
    "productName": "리페어 퍼퓸 샴푸 코튼 메모리",
    "productSelect": "퍼퓸 샴푸 코튼 메모리",
    "price": 65000,
    "productOption": "(30%) 샴푸+트리트먼트+헤어오일 (+37,000원)"
  },
  {
    "id": 197,
    "productCode": 34,
    "productName": "리페어 퍼퓸 샴푸 코튼 메모리",
    "productSelect": "퍼퓸 샴푸 코튼 메모리",
    "price": 68000,
    "productOption": "(30%) 샴푸+트리트먼트+퍼퓸샤워 (+40,000원)"
  },
  {
    "id": 198,
    "productCode": 35,
    "productName": "퍼퓸 디퓨저 코튼 허그",
    "productSelect": "코튼 허그 디퓨저",
    "price": 29000,
    "productOption": "코튼 허그 디퓨저 1개"
  },
  {
    "id": 199,
    "productCode": 35,
    "productName": "퍼퓸 디퓨저 코튼 허그",
    "productSelect": "코튼 허그 디퓨저",
    "price": 53000,
    "productOption": "코튼 허그 디퓨저 2개 (+23,000원)"
  },
  {
    "id": 200,
    "productCode": 35,
    "productName": "퍼퓸 디퓨저 코튼 허그",
    "productSelect": "코튼 허그 디퓨저",
    "price": 79000,
    "productOption": "코튼 허그 디퓨저 3개 (+50,000원)"
  },
  {
    "id": 201,
    "productCode": 36,
    "productName": "올라운드 퍼퓸 디퓨저 코튼 메모리",
    "productSelect": "코튼 메모리 디퓨저",
    "price": 29000,
    "productOption": "코튼 메모리 디퓨저 1개"
  },
  {
    "id": 202,
    "productCode": 36,
    "productName": "올라운드 퍼퓸 디퓨저 코튼 메모리",
    "productSelect": "코튼 메모리 디퓨저",
    "price": 53000,
    "productOption": "코튼 메모리 디퓨저 2개 (+23,000원)"
  },
  {
    "id": 203,
    "productCode": 36,
    "productName": "올라운드 퍼퓸 디퓨저 코튼 메모리",
    "productSelect": "코튼 메모리 디퓨저",
    "price": 79000,
    "productOption": "코튼 메모리 디퓨저 3개 (+50,000원)"
  },
  {
    "id": 204,
    "productCode": 37,
    "productName": "퍼퓸 샤워 바디 스크럽 코튼 메모리",
    "productSelect": "바디스크럽",
    "price": 19000,
    "productOption": "1개"
  },
  {
    "id": 205,
    "productCode": 37,
    "productName": "퍼퓸 샤워 바디 스크럽 코튼 메모리",
    "productSelect": "바디스크럽",
    "price": 33000,
    "productOption": "(34%off) 2개 (+14,000원)"
  },
  {
    "id": 206,
    "productCode": 37,
    "productName": "퍼퓸 샤워 바디 스크럽 코튼 메모리",
    "productSelect": "세트",
    "price": 43000,
    "productOption": "(28%) 바디스크럽+퍼퓸로션 (+24,000원)"
  },
  {
    "id": 207,
    "productCode": 37,
    "productName": "퍼퓸 샤워 바디 스크럽 코튼 메모리",
    "productSelect": "세트",
    "price": 43000,
    "productOption": "(28%) 바디스크럽+퍼퓸샤워 (+24,000원)"
  },
  {
    "id": 208,
    "productCode": 37,
    "productName": "퍼퓸 샤워 바디 스크럽 코튼 메모리",
    "productSelect": "세트",
    "price": 62000,
    "productOption": "(35%) 바디스크럽+퍼퓸샤워+퍼퓸로션 (+43,000원)"
  },
  {
    "id": 209,
    "productCode": 38,
    "productName": "리페어 퍼퓸 트리트먼트 코튼 메모리",
    "productSelect": "트리트먼트",
    "price": 19000,
    "productOption": "트리트먼트 1개"
  },
  {
    "id": 210,
    "productCode": 38,
    "productName": "리페어 퍼퓸 트리트먼트 코튼 메모리",
    "productSelect": "트리트먼트",
    "price": 36000,
    "productOption": "(25%) 트리트먼트 2개 (+17,000원)"
  },
  {
    "id": 211,
    "productCode": 38,
    "productName": "리페어 퍼퓸 트리트먼트 코튼 메모리",
    "productSelect": "트리트먼트",
    "price": 43500,
    "productOption": "(30%) 트리트먼트+퍼퓸샴푸 (+24,500원)"
  },
  {
    "id": 212,
    "productCode": 38,
    "productName": "리페어 퍼퓸 트리트먼트 코튼 메모리",
    "productSelect": "트리트먼트",
    "price": 65000,
    "productOption": "(30%) 샴푸+트리트먼트+헤어오일  (+46,000원)"
  },
  {
    "id": 213,
    "productCode": 38,
    "productName": "리페어 퍼퓸 트리트먼트 코튼 메모리",
    "productSelect": "트리트먼트",
    "price": 68000,
    "productOption": "(30%) 샴푸+트리트먼트+퍼퓸샤워 (+49,000원)"
  },
  {
    "id": 214,
    "productCode": 39,
    "productName": "리페어 퍼퓸 헤어오일 코튼 메모리",
    "productSelect": "단품",
    "price": 19000,
    "productOption": "퍼퓸 헤어오일 1개"
  },
  {
    "id": 215,
    "productCode": 39,
    "productName": "리페어 퍼퓸 헤어오일 코튼 메모리",
    "productSelect": "세트",
    "price": 63000,
    "productOption": "[EVENT] 퍼퓸+헤어오일(+미니어처 증정) (+44,000원)"
  },
  {
    "id": 216,
    "productCode": 39,
    "productName": "리페어 퍼퓸 헤어오일 코튼 메모리",
    "productSelect": "세트",
    "price": 43500,
    "productOption": "(30%) 헤어오일+퍼퓸샴푸 (+24,500원)"
  },
  {
    "id": 217,
    "productCode": 39,
    "productName": "리페어 퍼퓸 헤어오일 코튼 메모리",
    "productSelect": "세트",
    "price": 65000,
    "productOption": "(30%) 샴푸+트리트먼트+헤어오일 (+46,000원)"
  },
  {
    "id": 218,
    "productCode": 40,
    "productName": "시그니처 올인원 에센스 모이스처 플러스",
    "productSelect": "단품",
    "price": 29000,
    "productOption": "올인원 모이스처 플러스 1개"
  },
  {
    "id": 219,
    "productCode": 40,
    "productName": "시그니처 올인원 에센스 모이스처 플러스",
    "productSelect": "세트",
    "price": 54900,
    "productOption": "(50%) 모이스처 플러스 2개 (+25,900원)"
  },
  {
    "id": 220,
    "productCode": 40,
    "productName": "시그니처 올인원 에센스 모이스처 플러스",
    "productSelect": "세트",
    "price": 53900,
    "productOption": "(29%) 모이스처 플러스+시그니처 올인원 에센스 (+24,900원)"
  },
  {
    "id": 221,
    "productCode": 40,
    "productName": "시그니처 올인원 에센스 모이스처 플러스",
    "productSelect": "세트",
    "price": 47000,
    "productOption": "모이스처 플러스+시그니처 폼클렌저 (+18,000원)"
  },
  {
    "id": 222,
    "productCode": 41,
    "productName": "시그니처 올인원 에센스",
    "productSelect": "단품",
    "price": 28900,
    "productOption": "시그니처 올인원 1개"
  },
  {
    "id": 223,
    "productCode": 41,
    "productName": "시그니처 올인원 에센스",
    "productSelect": "세트",
    "price": 53800,
    "productOption": "(25%) 시그니처 올인원 에센스 2개 (+24,900원)"
  },
  {
    "id": 224,
    "productCode": 41,
    "productName": "시그니처 올인원 에센스",
    "productSelect": "세트",
    "price": 53900,
    "productOption": "(29%) 시그니처 올인원 에센스+모이스처 플러스 (+25,000원)"
  },
  {
    "id": 225,
    "productCode": 41,
    "productName": "시그니처 올인원 에센스",
    "productSelect": "세트",
    "price": 46900,
    "productOption": "시그니처 올인원 에센스+시그니처 폼클렌저 (+18,000원)"
  },
  {
    "id": 226,
    "productCode": 42,
    "productName": "올라운드 퍼퓸 디퓨저",
    "productSelect": "코튼허그",
    "price": 29000,
    "productOption": "1개"
  },
  {
    "id": 227,
    "productCode": 42,
    "productName": "올라운드 퍼퓸 디퓨저",
    "productSelect": "코튼키스",
    "price": 29000,
    "productOption": "1개"
  },
  {
    "id": 228,
    "productCode": 42,
    "productName": "올라운드 퍼퓸 디퓨저",
    "productSelect": "코튼메모리",
    "price": 29000,
    "productOption": "1개"
  },
  {
    "id": 229,
    "productCode": 43,
    "productName": "[RENEWAL] 퍼퓸 차량용방향제",
    "productSelect": "크롬블랙",
    "price": 48000,
    "productOption": "코튼허그"
  },
  {
    "id": 230,
    "productCode": 43,
    "productName": "[RENEWAL] 퍼퓸 차량용방향제",
    "productSelect": "크롬블랙",
    "price": 48000,
    "productOption": "허그 미"
  },
  {
    "id": 231,
    "productCode": 43,
    "productName": "[RENEWAL] 퍼퓸 차량용방향제",
    "productSelect": "크롬블랙",
    "price": 48000,
    "productOption": "로즈베이"
  },
  {
    "id": 232,
    "productCode": 43,
    "productName": "[RENEWAL] 퍼퓸 차량용방향제",
    "productSelect": "크롬블랙",
    "price": 48000,
    "productOption": "어웨이큰 미"
  },
  {
    "id": 233,
    "productCode": 43,
    "productName": "[RENEWAL] 퍼퓸 차량용방향제",
    "productSelect": "로즈골드",
    "price": 48000,
    "productOption": "코튼허그"
  },
  {
    "id": 234,
    "productCode": 43,
    "productName": "[RENEWAL] 퍼퓸 차량용방향제",
    "productSelect": "로즈골드",
    "price": 48000,
    "productOption": "허그 미"
  },
  {
    "id": 235,
    "productCode": 43,
    "productName": "[RENEWAL] 퍼퓸 차량용방향제",
    "productSelect": "로즈골드",
    "price": 48000,
    "productOption": "로즈베이"
  },
  {
    "id": 236,
    "productCode": 43,
    "productName": "[RENEWAL] 퍼퓸 차량용방향제",
    "productSelect": "로즈골드",
    "price": 48000,
    "productOption": "어웨이큰 미"
  },
  {
    "id": 237,
    "productCode": 43,
    "productName": "[RENEWAL] 퍼퓸 차량용방향제",
    "productSelect": "화이트펄",
    "price": 48000,
    "productOption": "코튼허그"
  },
  {
    "id": 238,
    "productCode": 43,
    "productName": "[RENEWAL] 퍼퓸 차량용방향제",
    "productSelect": "화이트펄",
    "price": 48000,
    "productOption": "허그 미"
  },
  {
    "id": 239,
    "productCode": 43,
    "productName": "[RENEWAL] 퍼퓸 차량용방향제",
    "productSelect": "화이트펄",
    "price": 48000,
    "productOption": "로즈베이"
  },
  {
    "id": 240,
    "productCode": 43,
    "productName": "[RENEWAL] 퍼퓸 차량용방향제",
    "productSelect": "화이트펄",
    "price": 48000,
    "productOption": "어웨이큰 미"
  },
  {
    "id": 241,
    "productCode": 43,
    "productName": "[RENEWAL] 퍼퓸 차량용방향제",
    "productSelect": "(한블리 콜라보)매트블랙",
    "price": 48000,
    "productOption": "어웨이큰 미"
  },
  {
    "id": 242,
    "productCode": 43,
    "productName": "[RENEWAL] 퍼퓸 차량용방향제",
    "productSelect": "(한블리 콜라보)매트블랙",
    "price": 48000,
    "productOption": "리멤버 미"
  },
  {
    "id": 243,
    "productCode": 44,
    "productName": "[RENEWAL]퍼퓸 차량용방향제 리필",
    "productSelect": "코튼허그",
    "price": 14000,
    "productOption": "1개"
  },
  {
    "id": 244,
    "productCode": 44,
    "productName": "[RENEWAL]퍼퓸 차량용방향제 리필",
    "productSelect": "코튼허그",
    "price": 26000,
    "productOption": "2개 (+12,000원)"
  },
  {
    "id": 245,
    "productCode": 44,
    "productName": "[RENEWAL]퍼퓸 차량용방향제 리필",
    "productSelect": "코튼허그",
    "price": 36000,
    "productOption": "3개 (+22,000원)"
  },
  {
    "id": 246,
    "productCode": 44,
    "productName": "[RENEWAL]퍼퓸 차량용방향제 리필",
    "productSelect": "코튼허그",
    "price": 44000,
    "productOption": "4개 (+30,000원)"
  },
  {
    "id": 247,
    "productCode": 44,
    "productName": "[RENEWAL]퍼퓸 차량용방향제 리필",
    "productSelect": "허그 미",
    "price": 14000,
    "productOption": "1개"
  },
  {
    "id": 248,
    "productCode": 44,
    "productName": "[RENEWAL]퍼퓸 차량용방향제 리필",
    "productSelect": "허그 미",
    "price": 26000,
    "productOption": "2개 (+12,000원)"
  },
  {
    "id": 249,
    "productCode": 44,
    "productName": "[RENEWAL]퍼퓸 차량용방향제 리필",
    "productSelect": "허그 미",
    "price": 36000,
    "productOption": "3개 (+22,000원)"
  },
  {
    "id": 250,
    "productCode": 44,
    "productName": "[RENEWAL]퍼퓸 차량용방향제 리필",
    "productSelect": "허그 미",
    "price": 44000,
    "productOption": "4개 (+30,000원)"
  },
  {
    "id": 251,
    "productCode": 44,
    "productName": "[RENEWAL]퍼퓸 차량용방향제 리필",
    "productSelect": "로즈베이",
    "price": 14000,
    "productOption": "1개"
  },
  {
    "id": 252,
    "productCode": 44,
    "productName": "[RENEWAL]퍼퓸 차량용방향제 리필",
    "productSelect": "로즈베이",
    "price": 26000,
    "productOption": "2개 (+12,000원)"
  },
  {
    "id": 253,
    "productCode": 44,
    "productName": "[RENEWAL]퍼퓸 차량용방향제 리필",
    "productSelect": "로즈베이",
    "price": 36000,
    "productOption": "3개 (+22,000원)"
  },
  {
    "id": 254,
    "productCode": 44,
    "productName": "[RENEWAL]퍼퓸 차량용방향제 리필",
    "productSelect": "로즈베이",
    "price": 44000,
    "productOption": "4개 (+30,000원)"
  },
  {
    "id": 255,
    "productCode": 44,
    "productName": "[RENEWAL]퍼퓸 차량용방향제 리필",
    "productSelect": "어웨이큰 미",
    "price": 14000,
    "productOption": "1개"
  },
  {
    "id": 256,
    "productCode": 44,
    "productName": "[RENEWAL]퍼퓸 차량용방향제 리필",
    "productSelect": "어웨이큰 미",
    "price": 26000,
    "productOption": "2개 (+12,000원)"
  },
  {
    "id": 257,
    "productCode": 44,
    "productName": "[RENEWAL]퍼퓸 차량용방향제 리필",
    "productSelect": "어웨이큰 미",
    "price": 36000,
    "productOption": "3개 (+22,000원)"
  },
  {
    "id": 258,
    "productCode": 44,
    "productName": "[RENEWAL]퍼퓸 차량용방향제 리필",
    "productSelect": "어웨이큰 미",
    "price": 44000,
    "productOption": "4개 (+30,000원)"
  },
  {
    "id": 259,
    "productCode": 45,
    "productName": "모이스처 퍼퓸 핸드워시 코튼 허그",
    "productSelect": "단품",
    "price": 19000,
    "productOption": "1개"
  },
  {
    "id": 260,
    "productCode": 45,
    "productName": "모이스처 퍼퓸 핸드워시 코튼 허그",
    "productSelect": "세트",
    "price": 35000,
    "productOption": "(27%) 핸드크림+핸드워시 (+16,000원)"
  },
  {
    "id": 261,
    "productCode": 46,
    "productName": "퍼퓸 핸드크림 코튼 허그",
    "productSelect": "단품",
    "price": 19000,
    "productOption": "핸드크림 1개"
  },
  {
    "id": 262,
    "productCode": 46,
    "productName": "퍼퓸 핸드크림 코튼 허그",
    "productSelect": "세트",
    "price": 35000,
    "productOption": "(27%) 핸드크림+핸드워시 (+16,000원)"
  },
  {
    "id": 263,
    "productCode": 46,
    "productName": "퍼퓸 핸드크림 코튼 허그",
    "productSelect": "세트",
    "price": 55000,
    "productOption": "(22%) 핸드크림+퍼퓸 (+36,000원)"
  },
  {
    "id": 264,
    "productCode": 46,
    "productName": "퍼퓸 핸드크림 코튼 허그",
    "productSelect": "세트",
    "price": 27000,
    "productOption": "[GIFT SET] 핸드크림+미니어처퍼퓸 (+8,000원)"
  },
  {
    "id": 265,
    "productCode": 46,
    "productName": "퍼퓸 핸드크림 코튼 허그",
    "productSelect": "세트",
    "price": 27000,
    "productOption": "[GIFT SET] 핸드크림+모이스처립밤 (+8,000원)"
  },
  {
    "id": 266,
    "productCode": 47,
    "productName": "모이스처 퍼퓸 핸드워시 코튼 메모리",
    "productSelect": "단품",
    "price": 19000,
    "productOption": "1개"
  },
  {
    "id": 267,
    "productCode": 47,
    "productName": "모이스처 퍼퓸 핸드워시 코튼 메모리",
    "productSelect": "세트",
    "price": 35000,
    "productOption": "(27%) 핸드크림+핸드워시 (+16,000원)"
  },
  {
    "id": 268,
    "productCode": 48,
    "productName": "퍼퓸 핸드크림 코튼 메모리",
    "productSelect": "단품",
    "price": 19000,
    "productOption": "1개"
  },
  {
    "id": 269,
    "productCode": 48,
    "productName": "퍼퓸 핸드크림 코튼 메모리",
    "productSelect": "세트",
    "price": 35000,
    "productOption": "(27%) 핸드크림+핸드워시 (+16,000원)"
  },
  {
    "id": 270,
    "productCode": 48,
    "productName": "퍼퓸 핸드크림 코튼 메모리",
    "productSelect": "세트",
    "price": 65000,
    "productOption": "(24%) 핸드크림+퍼퓸 (+46,000원)"
  },
  {
    "id": 271,
    "productCode": 48,
    "productName": "퍼퓸 핸드크림 코튼 메모리",
    "productSelect": "세트",
    "price": 27000,
    "productOption": "[GIFT SET] 핸드크림+미니어처퍼퓸 (+8,000원)"
  },
  {
    "id": 272,
    "productCode": 48,
    "productName": "퍼퓸 핸드크림 코튼 메모리",
    "productSelect": "세트",
    "price": 27000,
    "productOption": "[GIFT SET] 핸드크림+모이스처립밤 (+8,000원)"
  }
]